runrex/__init__.py
runrex/main.py
runrex/pytest_utils.py
runrex/schema.py
runrex/terms.py
runrex/util.py
runrex/algo/__init__.py
runrex/algo/annotation.py
runrex/algo/direction.py
runrex/algo/match.py
runrex/algo/matchcask.py
runrex/algo/negation.py
runrex/algo/pattern.py
runrex/algo/result.py
runrex/algo/utils.py
runrex/anlz/__init__.py
runrex/anlz/summary.py
runrex/cli/__init__.py
runrex/cli/build_review_lists.py
runrex/cli/create_variable.py
runrex/cli/extract_and_load_json.py
runrex/cli/generate_frequencies.py
runrex/cli/simplify_findings.py
runrex/io/__init__.py
runrex/io/corpus.py
runrex/io/formatter.py
runrex/io/out.py
runrex/io/report.py
runrex/io/sqlai.py
runrex/io/utils.py
runrex/post/__init__.py
runrex/post/build_review_lists.py
runrex/post/variable_builder.py
runrex/text/__init__.py
runrex/text/document.py
runrex/text/section.py
runrex/text/sections.py
runrex/text/sentence.py
runrex/text/sentences.py
runrex/text/ssplit.py
runrex-0.5.0.dist-info/LICENSE
runrex-0.5.0.dist-info/WHEEL
runrex-0.5.0.dist-info/METADATA
runrex-0.5.0.dist-info/RECORD
