Metadata-Version: 2.1
Name: runrex
Version: 0.5.0
Summary: Library to aid in organizing, running, and debugging regular expressions against large bodies of text.
Keywords: nlp,information extraction
Author-email: dcronkite <dcronkite+pypi@gmail.com>
Requires-Python: >=3.8
Classifier: Development Status :: 5 - Production/Stable
Classifier: Intended Audience :: Science/Research
Classifier: Programming Language :: Python :: 3 :: Only
Classifier: Topic :: Text Processing :: Linguistic
Classifier: License :: OSI Approved :: MIT License
Requires-Dist: pyodbc ; extra == "db"
Requires-Dist: pytest ; extra == "dev"
Requires-Dist: pandas ; extra == "pandas"
Requires-Dist: psycopg2 ; extra == "psql"
Requires-Dist: sas7bdat ; extra == "sas"
Requires-Dist: syntok ; extra == "tok"
Project-URL: Home, https://github.com/kpwhri/runrex
Provides-Extra: db
Provides-Extra: dev
Provides-Extra: pandas
Provides-Extra: psql
Provides-Extra: sas
Provides-Extra: tok
